Workbook

Sheet balance sheet
B1: 43525 | C1: 43891 | D1: 44256 | E1: 44621 | F1: 44986 | G1: 45352 | H1: 45741
A2: Equity Capital | B2: 24 | C2: 25 | D2: 25 | E2: 50 | F2: 55 | G2: 56 | H2: 56
A3: Reserves | B3: 940 | C3: 1331 | D3: 1670 | E3: 2414 | F3: 2950 | G3: 3549 | H3: 4153
A4: Borrowings - | B4: 858 | C4: 834 | D4: 520 | E4: 581 | F4: 873 | G4: 1144 | H4: 634
A5: Long term Borrowings | B5: 175 | C5: 404 | D5: 183 | E5: 347 | F5: 408 | G5: 787 | H5: 409
A6: Short term Borrowings | B6: 536 | C6: 323 | D6: 337 | E6: 233 | F6: 465 | G6: 338 | H6: 206
A7: Lease Liabilities | B7: 0 | C7: 1 | D7: 0 | E7: 1 | F7: 0 | G7: 20 | H7: 20
A8: Other Borrowings | B8: 148 | C8: 107 | D8: 0 | E8: 0 | F8: 0 | G8: 0 | H8: 0
A9: Other Liabilities - | B9: 952 | C9: 1075 | D9: 1184 | E9: 1407 | F9: 1973 | G9: 2438 | H9: 2753
A10: Non controlling int | B10: 0 | C10: 95 | D10: 138 | E10: 0 | F10: 0 | G10: 0 | H10: 0
A11: Trade Payables | B11: 699 | C11: 764 | D11: 786 | E11: 1059 | F11: 1597 | G11: 1982 | H11: 2231
A12: Advance from Customers | B12: 14 | C12: 7 | D12: 12 | E12: 28 | F12: 25 | G12: 32 | H12: 79
A13: Other liability items | B13: 239 | C13: 209 | D13: 248 | E13: 320 | F13: 351 | G13: 424 | H13: 443
... A38: Total Assets | B38: 2774 | C38: 3266 | D38: 3399 | E38: 4452 | F38: 5852 | G38: 7187 | H38: 7596

Sheet profit and loss account
B1: 43525 | C1: 43891 | D1: 44256 | E1: 44621 | F1: 44986 | G1: 45352 | H1: 45741 | I1: TTM
A2: Sales - | B2: 7152 | C2: 7723 | D2: 8500 | E2: 13063 | F2: 16166 | G2: 18119 | H2: 20690 | I2: 20885
A3: Sales Growth % | B3: 0.3407 | C3: 0.0798 | D3: 0.1005 | E3: 0.5369 | F3: 0.2375 | G3: 0.1208 | H3: 0.1419
A4: Expenses - | B4: 6759 | C4: 7246 | D4: 7821 | E4: 12118 | F4: 15143 | G4: 16926 | H4: 19490 | I4: 19616
A5: Material Cost % - | B5: 0.88 | C5: 0.85 | D5: 0.84 | E5: 0.86 | F5: 0.87 | G5: 0.86 | H5: 0.86
A6: Raw material cost | B6: 6396 | C6: 6712 | D6: 7227 | E6: 11160 | F6: 14609 | G6: 15626 | H6: 17793
A7: Change in inventory | B7: -88 | C7: -136 | D7: -62 | E7: 63 | F7: -582 | G7: -9 | H7: 78
A8: Manufacturing Cost % | B8: 0.02 | C8: 0.02 | D8: 0.02 | E8: 0.02 | F8: 0.02 | G8: 0.02 | H8: 0.02
A9: Employee Cost % | B9: 0.02 | C9: 0.02 | D9: 0.02 | E9: 0.01 | F9: 0.01 | G9: 0.01 | H9: 0.02
A10: Other Cost % | B10: 0.03 | C10: 0.04 | D10: 0.04 | E10: 0.04 | F10: 0.04 | G10: 0.04 | H10: 0.04
A11: Operating Profit | B11: 393 | C11: 478 | D11: 679 | E11: 946 | F11: 1022 | G11: 1193 | H11: 1199 | I11: 1269
A12: OPM % | B12: 0.05 | C12: 0.06 | D12: 0.08 | E12: 0.07 | F12: 0.06 | G12: 0.07 | H12: 0.06 | I12: 0.06
A13: Other Income - | B13: 12 | C13: 22 | D13: 36 | E13: 40 | F13: 46 | G13: 74 | H13: 96 | I13: 97
A14: Exceptional items | B14: 0 | C14: 1 | D14: 0 | E14: 0 | F14: -1 | G14: 5 | H14: 21
A15: Other income normal | B15: 12 | C15: 20 | D15: 36 | E15: 40 | F15: 47 | G15: 69 | H15: 74
A16: Interest | B16: 113 | C16: 107 | D16: 66 | E16: 44 | F16: 67 | G16: 113 | H16: 133 | I16: 139
A17: Depreciation | B17: 64 | C17: 96 | D17: 103 | E17: 109 | F17: 138 | G17: 176 | H17: 201 | I17: 209
A18: Profit before tax | B18: 227 | C18: 296 | D18: 546 | E18: 832 | F18: 863 | G18: 978 | H18: 960 | I18: 1018
A19: Tax % | B19: 0.35 | C19: 0.14 | D19: 0.25 | E19: 0.26 | F19: 0.26 | G19: 0.25 | H19: 0.21
A20: Net Profit - | B20: 148 | C20: 256 | D20: 408 | E20: 619 | F20: 642 | G20: 732 | H20: 757 | I20: 801
A21: Minority share | B21: 0 | C21: -18 | D21: -48 | E21: 0 | F21: 0 | G21: 0 | H21: 0
A22: Exceptional items AT | B22: 0 | C22: 1 | D22: 0 | E22: 0 | F22: -1 | G22: 4 | H22: 17
A23: Profit excl Excep | B23: 148 | C23: 255 | D23: 408 | E23: 619 | F23: 643 | G23: 729 | H23: 740
A24: Profit for PE | B24: 148 | C24: 237 | D24: 360 | E24: 619 | F24: 643 | G24: 729 | H24: 740
A25: Profit for EPS | B25: 148 | C25: 238 | D25: 360 | E25: 619 | F25: 642 | G25: 732 | H25: 757
A26: EPS in Rs | B26: 6.22 | C26: 9.58 | D26: 14.42 | E26: 24.73 | F26: 23.14 | G26: 26.39 | H26: 27.28 | I26: 28.87
A27: Dividend Payout % | B27: 0.23 | C27: 0 | D27: 0 | E27: 0.14 | F27: 0.22 | G27: 0.21 | H27: 0.21

Sheet cash flow statement
B1: 43525 | C1: 43891 | D1: 44256 | E1: 44621 | F1: 44986 | G1: 45352 | H1: 45741
A2: Cash from Operating Activity - | B2: 358 | C2: 510 | D2: 977 | E2: 652 | F2: 691 | G2: 1112 | H2: 1213
A3: Profit from operations | B3: 396 | C3: 489 | D3: 685 | E3: 966 | F3: 1055 | G3: 1205 | H3: 1228
A4: Receivables | B4: -112 | C4: 85 | D4: 347 | E4: -211 | F4: 199 | G4: -64 | H4: -29
A5: Inventory | B5: -192 | C5: 28 | D5: 23 | E5: -89 | F5: -634 | G5: -160 | H5: -120
A6: Payables | B6: 324 | C6: 26 | D6: 21 | E6: 274 | F6: 538 | G6: 385 | H6: 250
A7: Loans Advances | B7: -3 | C7: 5 | D7: 0 | E7: -3 | F7: -275 | G7: -61 | H7: -8
A8: Other WC items | B8: 12 | C8: -42 | D8: 20 | E8: -86 | F8: 25 | G8: 23 | H8: 81
A9: Working capital changes | B9: 29 | C9: 102 | D9: 412 | E9: -115 | F9: -147 | G9: 124 | H9: 173
A10: Direct taxes | B10: -67 | C10: -82 | D10: -119 | E10: -199 | F10: -216 | G10: -218 | H10: -188
A11: Cash from Investing Activity - | B11: -264 | C11: -435 | D11: -647 | E11: -530 | F11: -876 | G11: -916 | H11: -375
A12: Fixed assets purchased | B12: z | C12: -309 | D12: -287 | E12: -597 | F12: -862 | G12: -695 | H12: -722
A13: Fixed assets sold | B13: 11 | C13: 8 | D13: 7 | E13: 10 | F13: 20 | G13: 33 | H13: 71
A14: Investments purchased | B14: -39 | C14: 0 | D14: 0 | E14: -87 | F14: -27 | G14: -5 | H14: -36
A15: Investments sold | B15: 0 | C15: 0 | D15: 0 | E15: 0 | F15: 5 | G15: 1 | H15: 0
A16: Interest received | B16: 1 | C16: 4 | D16: 20 | E16: 15 | F16: 1 | G16: 39 | H16: 66
A17: Invest in subsidiaries | B17: 0 | C17: -142 | D17: 0 | E17: 0 | F17: 0 | G17: 0 | H17: 0
A18: Acquisition of companies | B18: 0 | C18: 0 | D18: -46 | E18: 0 | F18: 0 | G18: 0 | H18: 0
A19: Other investing items | B19: 0 | C19: 5 | D19: -341 | E19: 129 | F19: -12 | G19: -289 | H19: 247
A20: Cash from Financing Activity - | B20: -53 | C20: -78 | D20: -359 | E20: 26 | F20: 143 | G20: 27 | H20: -815
A21: Proceeds from shares | B21: 6 | C21: 177 | D21: 15 | E21: 7 | F21: 3 | G21: 3 | H21: 0
A22: Proceeds from borrowings | B22: 306 | C22: 383 | D22: 141 | E22: 239 | F22: 355 | G22: 546 | H22: 1152
A23: Repayment of borrowings | B23: -223 | C23: -478 | D23: -452 | E23: -178 | F23: -65 | G23: -288 | H23: -1666
A24: Interest paid fin | B24: -101 | C24: -119 | D24: -62 | E24: -41 | F24: -61 | G24: -94 | H24: -147
... A28: Net Cash Flow | B28: 41 | C28: -3 | D28: -28 | E28: 148 | F28: -41 | G28: 222 | H28: 24

Sheet key ratios
A1: Ratio | B1: 43891 | C1: 44256 | D1: 44621 | E1: 44986 | F1: 45352 | G1: 45717 | H1: trend line | I1: interpretations
A2: net income | B2: 256 | C2: 408 | D2: 619 | E2: 642 | F2: 732 | G2: 757 | I2: Net income rose steadily from ₹256 Cr (2020) to ₹757 Cr (2025), showing strong profit growth driven by rising sales and efficient operations.
A3: net sales | B3: 7723 | C3: 8500 | D3: 13063 | E3: 16166 | F3: 18119 | G3: 20690 | I3: Sales nearly tripled from ₹7,723 Cr (2020) to ₹20,690 Cr (2025), reflecting expanding market presence and strong demand.
A4: return on sales | B4: =B2/B3 -> 0.033147741 | C4: =C2/C3 -> 0.048 | D4: =D2/D3 -> 0.047385746 | E4: =E2/E3 -> 0.039712978 | F4: =F2/F3 -> 0.040399581 | G4: =G2/G3 -> 0.036587724 | I4: ROS improved from 3.3% to about 4%, showing better cost management and stable profitability despite rising expenses.
A5: asset turnover ratio | B5: =B3/'balance sheet'!C38 -> 2.3646663 | C5: =C3/'balance sheet'!D38 -> 2.5007355 | D5: =D3/'balance sheet'!E38 -> 2.9341869 | E5: =E3/'balance sheet'!F38 -> 2.7624744 | F5: =F3/'balance sheet'!G38 -> 2.5210797 | G5: =G3/'balance sheet'!H38 -> 2.723802 | I5: Slightly declined from 2.5 to 2.7, suggesting the company maintains efficient use of its assets to generate revenue, though asset base expansion slightly reduced turnover efficiency.
A6: return on assets | B6: =B2/'balance sheet'!C38 -> 0.078383344 | C6: =C2/'balance sheet'!D38 -> 0.1200353 | D6: =D2/'balance sheet'!E38 -> 0.13903863 | E6: =E2/'balance sheet'!F38 -> 0.10970608 | F6: =F2/'balance sheet'!G38 -> 0.10185056 | G6: =G2/'balance sheet'!H38 -> 0.099657715 | I6: ROA increased from 7.8% (2020) to 10% (2025), indicating that assets are generating better returns over time, supported by improved earnings.
A7: financial leverage | B7: ='balance sheet'!C38/'balance sheet'!C2 -> 130.64 | C7: ='balance sheet'!D38/'balance sheet'!D2 -> 135.96 | D7: ='balance sheet'!E38/'balance sheet'!E2 -> 89.04 | E7: ='balance sheet'!F38/'balance sheet'!F2 -> 106.4 | F7: ='balance sheet'!G38/'balance sheet'!G2 -> 128.33929 | G7: ='balance sheet'!H38/'balance sheet'!H2 -> 135.64286 | I7: Fluctuated between 89–136, implying moderate reliance on debt financing. The increasing leverage indicates higher risk but also potential for higher shareholder returns.
A8: return on equity | B8: =B2/'balance sheet'!C2 -> 10.24 | C8: =C2/'balance sheet'!D2 -> 16.32 | D8: =D2/'balance sheet'!E2 -> 12.38 | E8: =E2/'balance sheet'!F2 -> 11.672727 | F8: =F2/'balance sheet'!G2 -> 13.071429 | G8: =G2/'balance sheet'!H2 -> 13.517857 | I8: ROE improved from 10.2% to 13.5%, showing strong returns to shareholders and efficient capital utilization.
A9: current assets | B9: 1515.47 | C9: 1849.62 | D9: 2137.81 | E9: 2557.77 | F9: 3341.36 | G9: 3467 | I9: Grew from ₹1,515 Cr to ₹3,467 Cr, showing rising liquidity and working capital availability.
A10: current liabilities | B10: 1152.48 | C10: 1412.93 | D10: 1742.64 | E10: 2180.25 | F10: 2495.42 | G10: 2753 | I10: Increased from ₹1,152 Cr to ₹2,753 Cr, consistent with company expansion and larger operations.
A11: current ratio | B11: =B9/B10 -> 1.3149643 | C11: =C9/C10 -> 1.309067 | D11: =D9/D10 -> 1.2267651 | E11: =E9/E10 -> 1.1731545 | F11: =F9/F10 -> 1.338997 | G11: =G9/G10 -> 1.2593534 | I11: Remained stable around 1.2–1.3, indicating a balanced liquidity position and the ability to meet short-term obligations.
A12: cogs | B12: 6956.16 | C12: 7508.16 | D12: 11633.28 | E12: 14537.28 | F12: 16248.96 | G12: 18710.4 | I12: Increased from ₹6,956 Cr to ₹18,710 Cr, reflecting higher production volumes but also rising input costs.
A13: inventories | B13: ='balance sheet'!B30+'balance sheet'!C30/2 -> 1176 | C13: ='balance sheet'!C30+'balance sheet'!D30/2 -> 1164 | D13: ='balance sheet'!D30+'balance sheet'!E30/2 -> 1183.5 | E13: ='balance sheet'!E30+'balance sheet'!F30/2 -> 1587 | F13: ='balance sheet'!F30+'balance sheet'!G30/2 -> 2299 | G13: ='balance sheet'!G30+'balance sheet'!H30/2 -> 2449.5 | I13: Steadily increased from ₹1,176 Cr to ₹2,449 Cr, showing business growth and higher product availability for demand fulfillment.
A14: inventory turnover ratio | B14: =B12/B13 -> 5.915102 | C14: =C12/C13 -> 6.4503093 | D14: =D12/D13 -> 9.8295564 | E14: =E12/E13 -> 9.1602268 | F14: =F12/F13 -> 7.0678382 | G14: =G12/G13 -> 7.6384568 | I14: Fluctuated between 5.9 and 9.8, settling around 7.6 in 2025. It reflects efficient inventory management but slower turnover in recent years due to rising stock levels.
A15: receivables connections | B15: ='balance sheet'!C31/'key ratios'!B3 -> 0.06163408 | C15: ='balance sheet'!D33/'key ratios'!C3 -> 0.016117647 | D15: ='balance sheet'!E31/'key ratios'!D3 -> 0.026180816 | E15: ='balance sheet'!F31/'key ratios'!E3 -> 0.0084745763 | F15: ='balance sheet'!G31/'key ratios'!F3 -> 0.007671505 | G15: ='balance sheet'!H31/'key ratios'!G3 -> 0.012904785 | I15: Very low ratio, indicating efficient recovery of dues and strong credit management practices
A16: revenue growth | B16: ='key ratios'!B3-'profit and loss account'!B2/'profit and loss account'!B2 -> 7722 | C16: =C3-B3/B3 -> 8499 | D16: =D3-C3/C3 -> 13062 | E16: =D3-E3/D3 -> 13061.762 | F16: =F3-E3/E3 -> 18118 | G16: =F3-G3/F3 -> 18117.858 | I16: Consistently positive, confirming steady top-line growth each year as the company expands production and sales volume.
A17: gross margin | B17: =B3-B12/B3 -> 7722.0993 | C17: =C3-C12/C3 -> 8499.1167 | D17: =D3-D12/D3 -> 13062.109 | E17: =E3-E12/E3 -> 16165.101 | F17: =F3-F12/F3 -> 18118.103 | G17: =G3-G12/G3 -> 20689.096 | I17: Shows stability, meaning production and operational efficiency remain under control even with increasing scale.
A18: divident payout | B18: ='cash flow statement'!C25/'key ratios'!B2 -> -0.1328125 | C18: ='cash flow statement'!D25/'key ratios'!C2 -> 0 | D18: ='cash flow statement'!E25/'key ratios'!D2 -> 0 | E18: ='cash flow statement'!F25/'key ratios'!E2 -> -0.13707165 | F18: ='cash flow statement'!G25/'key ratios'!F2 -> -0.18989071 | G18: ='cash flow statement'!H25/'key ratios'!G2 -> -0.20211361 | I18: Fluctuated between small negative and zero values — indicates retained profits are reinvested in business expansion rather than distributed as dividends.
A19: R &D ratio

Sheet key financial performance indi
B1: 43891 | C1: 44256 | D1: 44621 | E1: 44986 | F1: 45352 | G1: 45717
A2: ebt margin | B2: =('profit and loss account'!C11/'profit and loss account'!C2)*100 -> 6.1893047 | C2: =('profit and loss account'!D11/'profit and loss account'!D2)*100 -> 7.9882353 | D2: =('profit and loss account'!D11/'profit and loss account'!E2)*100 -> 5.1978872 | E2: =('profit and loss account'!E11/'profit and loss account'!F2)*100 -> 5.8517877 | F2: =('profit and loss account'!F11/'profit and loss account'!G2)*100 -> 5.6404879 | G2: =('profit and loss account'!G11/'profit and loss account'!H2)*100 -> 5.7660706
A3: free cash flow | B3: ='cash flow statement'!C2-'cash flow statement'!C12 -> 819 | C3: ='cash flow statement'!D2-'cash flow statement'!D12 -> 1264 | D3: ='cash flow statement'!E2-'cash flow statement'!E12 -> 1249 | E3: ='cash flow statement'!F2-'cash flow statement'!F12 -> 1553 | F3: ='cash flow statement'!G2-'cash flow statement'!G12 -> 1807 | G3: ='cash flow statement'!H2-'cash flow statement'!H12 -> 1935 | I3: ebita margin= (ebita/total sales)*100
A4: working capital | B4: ='key ratios'!B9-'key ratios'!B10 -> 362.99 | C4: ='key ratios'!C9-'key ratios'!C10 -> 436.69 | D4: ='key ratios'!D9-'key ratios'!D10 -> 395.17 | E4: ='key ratios'!E9-'key ratios'!E10 -> 377.52 | F4: ='key ratios'!F9-'key ratios'!F10 -> 845.94 | G4: ='key ratios'!G9-'key ratios'!G10 -> 714 | I4: free cash flow= cah flow from operating activities- capital expenditure
A5: liquid capital | B5: =('balance sheet'!C35+'balance sheet'!C31)-('key ratios'!B10+'balance sheet'!C5) -> -1034.48 | C5: =('balance sheet'!D35+'balance sheet'!D31)-('key ratios'!C10+'balance sheet'!D5) -> -1106.93 | D5: =('balance sheet'!E35+'balance sheet'!E31)-('key ratios'!D10+'balance sheet'!E5) -> -1371.64 | E5: =('balance sheet'!F35+'balance sheet'!F31)-('key ratios'!E10+'balance sheet'!F5) -> -2099.25 | F5: =('balance sheet'!G35+'balance sheet'!G31)-('key ratios'!F10+'balance sheet'!G5) -> -2795.42 | G5: =('balance sheet'!H35+'balance sheet'!H31)-('key ratios'!G10+'balance sheet'!H5) -> -2320
A6: NOPAT | B6: =('key ratios'!B2+'profit and loss account'!C18+'profit and loss account'!C16+'profit and loss account'!C13+'profit and loss account'!C14)*(1-'profit and loss account'!C19) -> 586.52 | C6: =('key ratios'!C2+'profit and loss account'!D18+'profit and loss account'!D16+'profit and loss account'!D13+'profit and loss account'!D14)*(1-'profit and loss account'!D19) -> 792 | D6: =('key ratios'!D2+'profit and loss account'!E18+'profit and loss account'!E16+'profit and loss account'!E13+'profit and loss account'!E14)*(1-'profit and loss account'!E19) -> 1135.9 | E6: =('key ratios'!E2+'profit and loss account'!F18+'profit and loss account'!F16+'profit and loss account'!F13+'profit and loss account'!F14)*(1-'profit and loss account'!F19) -> 1196.58 | F6: =('key ratios'!F2+'profit and loss account'!G18+'profit and loss account'!G16+'profit and loss account'!G13+'profit and loss account'!G14)*(1-'profit and loss account'!G19) -> 1426.5 | G6: =('key ratios'!G2+'profit and loss account'!H18+'profit and loss account'!H16+'profit and loss account'!H13+'profit and loss account'!H14)*(1-'profit and loss account'!H19) -> 1553.93 | J6: "here capital expeniture means total assets purchased"
A7: Net int. exp after tax | B7: ='profit and loss account'!C16*(1-'profit and loss account'!C19) -> 92.02 | C7: ='profit and loss account'!D16*(1-'profit and loss account'!D19) -> 49.5 | D7: ='profit and loss account'!E16*(1-'profit and loss account'!E19) -> 32.56 | E7: ='profit and loss account'!F16*(1-'profit and loss account'!F19) -> 49.58 | F7: ='profit and loss account'!G16*(1-'profit and loss account'!G19) -> 84.75 | G7: ='profit and loss account'!H16*(1-'profit and loss account'!H19) -> 105.07
A8: int. bearing liabilities | B8: ='balance sheet'!C5+'balance sheet'!C6+'balance sheet'!C7+'balance sheet'!C8 -> 835 | C8: ='balance sheet'!D5+'balance sheet'!D6+'balance sheet'!D7+'balance sheet'!D8 -> 520 | D8: ='balance sheet'!E5+'balance sheet'!E6+'balance sheet'!E7+'balance sheet'!E8 -> 581 | E8: ='balance sheet'!F5+'balance sheet'!F6+'balance sheet'!F7+'balance sheet'!F8 -> 873 | F8: ='balance sheet'!G5+'balance sheet'!G6+'balance sheet'!G7+'balance sheet'!G8 -> 1145 | G8: ='balance sheet'!H5+'balance sheet'!H6+'balance sheet'!H7+'balance sheet'!H8 -> 635 | J8: working capital= ca-cl
A9: net long term assets | B9: ='balance sheet'!C25-'balance sheet'!C26 -> 1708 | C9: ='balance sheet'!D25-'balance sheet'!D26 -> 1735 | D9: ='balance sheet'!E25-'balance sheet'!E26 -> 1837 | E9: ='balance sheet'!F25-'balance sheet'!F26 -> 2580 | F9: ='balance sheet'!G25-'balance sheet'!G26 -> 3281 | G9: ='balance sheet'!H25-'balance sheet'!H26 -> 3668
A10: net debt | B10: ='balance sheet'!C14-'balance sheet'!C35 -> 3220 | C10: ='balance sheet'!D14-'balance sheet'!D35 -> 3041 | D10: ='balance sheet'!E14-'balance sheet'!E35 -> 4076 | E10: ='balance sheet'!F14-'balance sheet'!F35 -> 5500 | F10: ='balance sheet'!G14-'balance sheet'!G35 -> 6839 | G10: ='balance sheet'!H14-'balance sheet'!H35 -> 7021 | J10: need to check short or long term lease and other liability items that it comes in current liabilties section or not with the help of annual report
A11: net assets | B11: ='balance sheet'!C38-'balance sheet'!C14 -> 0 | C11: ='balance sheet'!D38-'balance sheet'!D14 -> 0 | D11: ='balance sheet'!E38-'balance sheet'!E14 -> 0 | E11: ='balance sheet'!F38-'balance sheet'!F14 -> 0 | F11: ='balance sheet'!G38-'balance sheet'!G14 -> 0 | G11: ='balance sheet'!H38-'balance sheet'!H14 -> 0
A12: net capital | B12: ='balance sheet'!C2+'balance sheet'!C3 -> 1356 | C12: ='balance sheet'!D2+'balance sheet'!D3 -> 1695 | D12: ='balance sheet'!E2+'balance sheet'!E3 -> 2464 | E12: ='balance sheet'!F2+'balance sheet'!F3 -> 3005 | F12: ='balance sheet'!G2+'balance sheet'!G3 -> 3605 | G12: ='balance sheet'!H2+'balance sheet'!H3 -> 4209 | I12: liquid capital= (cash equialents+ marketable securites+ accounts receivable)-current liabilities+ long term debt)
A13: working capital turnover ratio | B13: ='key ratios'!B3/'key financial performance indi'!B4 -> 21.276068 | C13: ='key ratios'!C3/'key financial performance indi'!C4 -> 19.464609 | D13: ='key ratios'!D3/'key financial performance indi'!D4 -> 33.056659 | E13: ='key ratios'!E3/'key financial performance indi'!E4 -> 42.821572 | F13: ='key ratios'!F3/'key financial performance indi'!F4 -> 21.418777 | G13: ='key ratios'!G3/'key financial performance indi'!G4 -> 28.977591 | I13: NOPAT= net operating prfit after tax/operating indicators
A14: basic eps | B14: ='key ratios'!B2-'cash flow statement'!C25/'KEY FINANCIALS'!J14 -> 256 | C14: ='key ratios'!C2-'cash flow statement'!D25/'KEY FINANCIALS'!J14 -> 408 | D14: ='key ratios'!D2-'cash flow statement'!E25/'KEY FINANCIALS'!J14 -> 619 | E14: ='key ratios'!E2-'cash flow statement'!F25/'KEY FINANCIALS'!J14 -> 642 | F14: ='key ratios'!F2-'cash flow statement'!G25/'KEY FINANCIALS'!J14 -> 732 | G14: ='key ratios'!G2-'cash flow statement'!H25/'KEY FINANCIALS'!J14 -> 757 | I14: NOPAT= net income+ tax+ int+ non-operating gains/losses*(1-tax rate)
A15: bvps | B15: ='balance sheet'!C2+'balance sheet'!C3/'KEY FINANCIALS'!J14 -> 25.000005 | C15: ='balance sheet'!D2+'balance sheet'!D3/'KEY FINANCIALS'!J14 -> 25.000006 | D15: ='balance sheet'!E2+'balance sheet'!E3/'KEY FINANCIALS'!J14 -> 50.000009 | E15: ='balance sheet'!F2+'balance sheet'!F3/'KEY FINANCIALS'!J14 -> 55.000011 | F15: ='balance sheet'!G2+'balance sheet'!G3/'KEY FINANCIALS'!J14 -> 56.000013 | G15: ='balance sheet'!H2+'balance sheet'!H3/'KEY FINANCIALS'!J14 -> 56.000015 | I15: net interest expense after tax= int exp.(1-tax rate)
A16: diluted eps | I16: int.bearing liablities= lomg term borrowings+short term borrowings+ lease liablities+ other borrowings
A17: p/b ratio | B17: 61.932 | C17: 61.932 | D17: 30.966 | E17: 28.1 | F17: 27.64 | G17: 27.6 | I17: net long term assets=Gross fixed assets (GFA) OR GROSS BLOCK -accumuted dep.
I18: Net debt= total debt- cash
I19: here cash includes cash equialents
I20: Net assets= total assets- toal liablities
I21: p/b ratio= market price per share/book value per share
B25: EBT margin remains stable between 5–8%, reflecting consistent profitability. Free cash flow and working capital improve annually, suggesting healthy financial management and operational efficiency.

Sheet KEY FINANCIALS
B1: 2020 | C1: 2021 | D1: 2022 | E1: 2023 | F1: 2024 | G1: 2025
A2: variable cost | B2: ='profit and loss account'!C5+'profit and loss account'!C8+'profit and loss account'!C9+'profit and loss account'!C10 -> 0.93 | C2: ='profit and loss account'!D5+'profit and loss account'!D8+'profit and loss account'!D9+'profit and loss account'!D10 -> 0.92 | D2: ='profit and loss account'!E5+'profit and loss account'!E8+'profit and loss account'!E9+'profit and loss account'!E10 -> 0.93 | E2: ='profit and loss account'!F5+'profit and loss account'!F8+'profit and loss account'!F9+'profit and loss account'!F10 -> 0.94 | F2: ='profit and loss account'!G5+'profit and loss account'!G8+'profit and loss account'!G9+'profit and loss account'!G10 -> 0.93 | G2: ='profit and loss account'!H5+'profit and loss account'!H8+'profit and loss account'!H9+'profit and loss account'!H10 -> 0.94
A3: contribution | B3: ='key ratios'!B3-'KEY FINANCIALS'!B2 -> 7722.07 | C3: ='key ratios'!C3-'KEY FINANCIALS'!C2 -> 8499.08 | D3: ='key ratios'!D3-'KEY FINANCIALS'!D2 -> 13062.07 | E3: ='key ratios'!E3-'KEY FINANCIALS'!E2 -> 16165.06 | F3: ='key ratios'!F3-'KEY FINANCIALS'!F2 -> 18118.07 | G3: ='key ratios'!G3-'KEY FINANCIALS'!G2 -> 20689.06 | J3: ebit=op-dep
A4: ebit | B4: ='profit and loss account'!C11-'profit and loss account'!C17 -> 382 | C4: ='profit and loss account'!D11-'profit and loss account'!D17 -> 576 | D4: ='profit and loss account'!E11-'profit and loss account'!E17 -> 837 | E4: ='profit and loss account'!F11-'profit and loss account'!F17 -> 884 | F4: ='profit and loss account'!G11-'profit and loss account'!G17 -> 1017 | G4: ='profit and loss account'!H11-'profit and loss account'!H17 -> 998 | J4: degree of leverage(dol)= contribution/ebit
J5: contribution= sales-vc
A6: operating leverage | B6: =B3/B4 -> 20.214843 | C6: =C3/C4 -> 14.755347 | D6: =D3/D4 -> 15.605818 | E6: =E3/E4 -> 18.286267 | F6: =F3/F4 -> 17.815211 | G6: =G3/G4 -> 20.730521 | J6: variable cost= manufacturing cst+material costs+others
J7: ebit=sales-vc-fc
J8: if fc is high then high risk company then operating leverage also is high
A9: ebt | B9: 296 | C9: 546 | D9: 832 | E9: 863 | F9: 978 | G9: 960
A10: financial leverage | B10: =B4/B9 -> 1.2905405 | C10: =C4/C9 -> 1.0549451 | D10: =D4/D9 -> 1.0060096 | E10: =E4/E9 -> 1.0243337 | F10: =F4/F9 -> 1.0398773 | G10: =G4/G9 -> 1.0395833 | J10: debt financial leverage(dfl)= ebit/ebt
J11: ebt= ebit -int
A12: total leverage | B12: =B6*B10 -> 26.088074 | C12: =C6*C10 -> 15.566081 | D12: =D6*D10 -> 15.699603 | E12: =E6*E10 -> 18.73124 | F12: =F6*F10 -> 18.525634 | G12: =G6*G10 -> 21.551104
J14: 277524564 | K14: shares outstanding value from thr annual report
J15: 1548.30 value of the marekt value per share
J16: total leverage= dfl*dol OR contribution/ebt
D19: EBIT and contribution increase year by year, showing enhanced operational efficiency. The variable cost ratio remains almost constant, indicating controlled cost structures. Degree of leverage shows steady performance.

Sheet FORMULAS 
A1: net capital= equity capital+ reserves
A3: working capital= ca-cl
A4: working capital turnover ratio= sales/ working capital | K4: shares otstanding means all the shares available in the market for trading
A5: basic eps=net income-dividend payments/weighted average shares outstanding
K6: weighted means perferance and equity shares
K7: diluted eps= net income-perferred dividents/ | O7: /weighted average of dilted common shares outstanding
A8: cash eps= operating cash flow/shares outstanding
A9: book value/per share= shareholder's equity-perfeered equity/no. of outstanding shares | M9: perferance share value in perferace dividents
A11: price/book value (price/bv)
A12: p/b ratio= market value per share/bok value per share
A13: ratio>1 states that market values the company higher than its book value, often due to growth | I13: prospects
A14: ratio<1 may indicate undervaluation or potential issues

Sheet QUESTION
A1: there are 2 firms A and B, A has a capital of rs.100000 and 0 debt and B has 50000 capital and 50000 debt. Interest rate on debt is 10%. EBIT of both the companies is 20000 and 30% tax. Compute ROE.
A5: ROE= Net profit (PAT,EAT,NET INCOME)/ shareholder's equity
A7: interest=50000*10/100 | C7: =5000 -> 5000
B8: tax | C8: EBIT | D8: EBT
B9: 0.3 | C9: 20000 | D9: 20000-0=20000
B10: 0.3 | C10: 20000 | D10: 20000-5000=15000
B11: Net profit
B12: EBT A=20000
B13: B=15000
B14: EBT tax(30%) | C14: A=6000
C15: B=4000
B16: then, EBT=(1-0.3)
B17: A=14000
B18: B=10,500
A20: FOR A= | B20: ROE=NP/E | C20: 14000/100000=14%
A22: FOR B= | B22: 10500/50000 | C22: 0.21
B24: unlevered firm= no debt= capital structure= 100% equity
B25: levered firm= has debt along with equity in capital structure.
B26: interest=
B27: Kd= Cost of Debt

Sheet fcff
B1: free cash flow firm
B2: 43891 | C2: 44256 | D2: 44621 | E2: 44986 | F2: 45352 | G2: 45717
A3: Ebit calculations | B3: PBT+INTEREST
A4: profit before tax | B4: 296 | C4: 546 | D4: 832 | E4: 863 | F4: 978 | G4: 960
A5: add interest | B5: 107 | C5: 66 | D5: 44 | E5: 67 | F5: 113 | G5: 133
A6: ebit | B6: =B4+B5 -> 403 | C6: =C4+C5 -> 612 | D6: =D4+D5 -> 876 | E6: =E4+E5 -> 930 | F6: =F4+F5 -> 1091 | G6: =G4+G5 -> 1093 | K6: fcff= | L6: NOPAT+ Depreciation and Amoritzation- CAPEX-Net Working Capital
A7: tax rate | B7: 0.14 | C7: 0.25 | D7: 0.26 | E7: 0.26 | F7: 0.25 | G7: 0.21 | K7: FCFF= EBIT*(1-TAX RATE)+DEPRECIATION AND AMORIZATION- CHANGE IN WORKING CAPITAL- CAPITAL EXPENDITURE
A8: EBIT*(1-tax rate) NOPAT | B8: =B6*(1-B7) -> 346.58 | C8: =C6*(1-C7) -> 459 | D8: =D6*(1-D7) -> 648.24 | E8: =E6*(1-E7) -> 688.2 | F8: =F6*(1-F7) -> 818.25 | G8: =G6*(1-G7) -> 863.47
A9: Depreciation | B9: 96 | C9: 103 | D9: 109 | E9: 138 | F9: 176 | G9: 201
A10: Working capital calculations | B10: current assets- current liablities
A11: Current Assets | B11: 1515.47 | C11: 1849.62 | D11: 2137.81 | E11: 2557.77 | F11: 3341.36 | G11: 3467
A12: Curent liabilities | B12: 1152.48 | C12: 1412.93 | D12: 1742.64 | E12: 2180.25 | F12: 2495.42 | G12: 2753
A13: Working capital | B13: =B11-B12 -> 362.99 | C13: =C11-C12 -> 436.69 | D13: =D11-D12 -> 395.17 | E13: =E11-E12 -> 377.52 | F13: =F11-F12 -> 845.94 | G13: =G11-G12 -> 714
A14: Changes in Working Capital | B14: Current working capital- previous working capital
C15: =C13-B13 -> 73.7 | D15: =D13-C13 -> -41.52 | E15: =E13-D13 -> -17.65 | F15: =F13-E13 -> 468.42 | G15: =G13-F13 -> -131.94
A16: CAPEX calculation | B16: Net change in fixed assets+ Depreciation
A17: Fixed assets | B17: 1708 | C17: 1736 | D17: 1837 | E17: 2580 | F17: 3281 | G17: 3668
A18: net increase in fixed assets | C18: =C17-B17 -> 28 | D18: =D17-C17 -> 101 | E18: =E17-D17 -> 743 | F18: =F17-E17 -> 701 | G18: =G17-F17 -> 387
A19: Depreciation | B19: 96 | C19: 103 | D19: 109 | E19: 138 | F19: 176 | G19: 201
A20: CAPEX calculation | B20: =B18+B19 -> 96 | C20: =C18+C19 -> 131 | D20: =D18+D19 -> 210 | E20: =E18+E19 -> 881 | F20: =F18+F19 -> 877 | G20: =G18+G19 -> 588
A21: Growth rates(21%)
A22: fcff | B22: =B8+B19-B20-B13 -> -16.41 | C22: =C8+C19-C20-C13 -> -5.69 | D22: =D8+D19-D20-D13 -> 152.07 | E22: =E8+E19-E20-E13 -> -432.32 | F22: =F8+F19-F20-F13 -> -728.69 | G22: =G8+G19-G20-G13 -> -237.53
A23: NPV (10%) | B23: =NPV(10%,B20,G20) -> 573.22314

Sheet simulation analysis
A1: MONTE CARLO SIMULATION
B2: PBT | C2: INTEREST | D2: CALCULATE EBIT | E2: TAX | F2: EBIT(1-tax) | G2: DEPRECIATION | H2: WORKING CAPITAL CHANGES | I2: CAPEX | J2: FCFF
A3: Average | B3: =AVERAGE(fcff!B4:G4) -> 745.83333 | C3: =AVERAGE(fcff!B5:G5) -> 88.333333 | D3: =AVERAGE(fcff!B6:G6) -> 834.16667 | E3: =AVERAGE(fcff!B7:G7) -> 0.22833333 | F3: =AVERAGE(fcff!B8:G8) -> 637.29 | G3: =AVERAGE(fcff!B9:G9) -> 137.16667 | H3: =AVERAGE(fcff!C15:G15) -> 70.202 | I3: =AVERAGE(fcff!B20:G20) -> 463.83333 | J3: =AVERAGE(fcff!B22:G22) -> -211.42833
A4: standard deviation | B4: =_xlfn.STDEV.S(fcff!B4:G4) -> 269.51988 | C4: =_xlfn.STDEV.S(fcff!B5:G5) -> 34.267575 | D4: =_xlfn.STDEV.S(fcff!B6:G6) -> 275.37423 | E4: =_xlfn.STDEV.S(fcff!B7:G7) -> 0.04708149 | F4: =_xlfn.STDEV.S(fcff!B8:G8) -> 201.45236 | G4: =_xlfn.STDEV.S(fcff!B9:G9) -> 42.985657 | H4: =_xlfn.STDEV.S(fcff!C15:G15) -> 234.33469 | I4: =_xlfn.STDEV.S(fcff!B20:G20) -> 366.24113 | J4: =_xlfn.STDEV.S(fcff!B22:G22) -> 325.43064
A6: FIRST ITERATION | B6: =_xlfn.NORM.INV(RAND(),B3,B4) -> 805.06513 | C6: =_xlfn.NORM.INV(RAND(),C3,C4) -> 94.773146 | D6: =_xlfn.NORM.INV(RAND(),D3,D4) -> 1303.6833 | E6: =_xlfn.NORM.INV(RAND(),E3,E4) -> 0.25137422 | F6: =_xlfn.NORM.INV(RAND(),F3,F4) -> 457.22323 | G6: =_xlfn.NORM.INV(RAND(),G3,G4) -> 124.78682 | H6: =_xlfn.NORM.INV(RAND(),H3,H4) -> 83.161651 | I6: =_xlfn.NORM.INV(RAND(),I3,I4) -> 545.45111 | J6: =_xlfn.NORM.INV(RAND(),J3,J4) -> -15.90052
A8: Simulation Number | B8: NOPAT | C8: Simulation Number | D8: DEPRECIATION | E8: Simulation Number | F8: WORKING CAPITAL CHANGES | G8: Simulation Number | H8: CAPEX | I8: Simulation Number | J8: FCFF
A9: 1 | B9: =F6 -> 457.22323 | C9: 1 | D9: =F6 -> 457.22323 | E9: 1 | F9: =H6 -> 83.161651 | G9: 1 | H9: =I6 -> 545.45111 | I9: 1 | J9: =J6 -> -15.90052
A10: 2 | B10: 671.29858 | C10: 2 | D10: 514.04857 | E10: 2 | F10: -64.50146 | G10: 2 | H10: 171.95619 | I10: 2 | J10: 424.69491
A11: 3 | B11: 823.26934 | C11: 3 | D11: 564.21797 | E11: 3 | F11: 372.06265 | G11: 3 | H11: -140.02203 | I11: 3 | J11: -191.24416
A12: 4 | B12: 464.11487 | C12: 4 | D12: 638.95678 | E12: 4 | F12: -212.89912 | G12: 4 | H12: 348.30424 | I12: 4 | J12: -680.27189
A13: 5 | B13: 153.02734 | C13: 5 | D13: 811.71967 | E13: 5 | F13: -22.772507 | G13: 5 | H13: 752.66519 | I13: 5 | J13: 38.947949
A14: 6 | B14: 890.77659 | C14: 6 | D14: 457.32884 | E14: 6 | F14: 258.3726 | G14: 6 | H14: 700.35096 | I14: 6 | J14: -459.96369
A15: 7 | B15: 1001.1554 | C15: 7 | D15: 616.41499 | E15: 7 | F15: 259.32762 | G15: 7 | H15: 771.06935 | I15: 7 | J15: 50.631753
A16: 8 | B16: 752.25507 | C16: 8 | D16: 618.66657 | E16: 8 | F16: 300.40857 | G16: 8 | H16: 125.07746 | I16: 8 | J16: 221.39726
A17: 9 | B17: 926.03253 | C17: 9 | D17: 502.54421 | E17: 9 | F17: 61.891845 | G17: 9 | H17: 825.75382 | I17: 9 | J17: 192.13532
A18: 10 | B18: 642.22371 | C18: 10 | D18: 323.16936 | E18: 10 | F18: 460.5452 | G18: 10 | H18: 275.3977 | I18: 10 | J18: 51.42398
A19: 11 | B19: 581.85379 | C19: 11 | D19: 532.4302 | E19: 11 | F19: -5.1345065 | G19: 11 | H19: 426.6788 | I19: 11 | J19: 212.68989
A20: 12 | B20: 1138.9994 | C20: 12 | D20: 611.59064 | E20: 12 | F20: 275.09296 | G20: 12 | H20: 1015.1288 | I20: 12 | J20: -207.68054
A21: 13 | B21: 814.94372 | C21: 13 | D21: 659.49981 | E21: 13 | F21: -185.64162 | G21: 13 | H21: 823.9402 | I21: 13 | J21: -300.14554
... A1008: 1000 | B1008: 266.67679 | C1008: 1000 | D1008: 332.30789 | E1008: 1000 | F1008: -21.002474 | G1008: 1000 | H1008: 33.553608 | I1008: 1000 | J1008: -301.66635
C1011: Simulation values
D1012: NOPAT | E1012: DEPRECIATION | F1012: WORKING CAPITAL CHANGES | G1012: CAPEX | H1012: FCFF
C1013: mean | D1013: =AVERAGE(B9:B1008) -> 642.52272 | E1013: =AVERAGE(D9:D1008) -> 637.36915 | F1013: =AVERAGE(F9:F1008) -> 73.352616 | G1013: =AVERAGE(H9:H1008) -> 482.09512 | H1013: =AVERAGE(J9:J1008) -> -188.27743
C1014: median | D1014: =MEDIAN(B9:B1008) -> 648.05036 | E1014: =MEDIAN(D9:D1008) -> 635.59015 | F1014: =MEDIAN(F9:F1008) -> 69.394441 | G1014: =MEDIAN(H9:H1008) -> 485.13517 | H1014: =MEDIAN(J9:J1008) -> -184.41713
C1015: standard deviation | D1015: =_xlfn.STDEV.S(B9:B1008) -> 202.42321 | E1015: =_xlfn.STDEV.S(F9:F1008) -> 227.36556 | F1015: =_xlfn.STDEV.S(F9:F1008) -> 227.36556 | G1015: =_xlfn.STDEV.S(H9:H1008) -> 360.9112 | H1015: =_xlfn.STDEV.S(J9:J1008) -> 323.70283
C1016: maximum | D1016: =MAX(B9:B1008) -> 1281.3259 | E1016: =MAX(D9:D1008) -> 1262.389 | F1016: =MAX(F9:F1008) -> 823.10329 | G1016: =MAX(H9:H1008) -> 1673.1856 | H1016: =MAX(J9:J1008) -> 780.6665
C1017: minimum | D1017: =MIN(B9:B1008) -> -17.686461 | E1017: =MIN(D9:D1008) -> 37.937862 | F1017: =MIN(F9:F1008) -> -573.80849 | G1017: =MIN(H9:H1008) -> -625.39691 | H1017: =MIN(J9:J1008) -> -1310.2988

Sheet ABOUT THE COMPANY
A1: APL Apollo Tubes Limited – Company Overview
A3: Incorporation & Identity
A5: Founded: February 24, 1986
A7: CIN: L74899DL1986PLC023443
A9: Registered Office: 37 Hargobind Enclave, Vikas Marg, Delhi 110092
A11: Corporate Office: SG Centre, 37C Block B, Sector 132, Noida (U.P.)
A12: Stock Listing: NSE – APLAPOLLO | BSE – 533758
A13: Business Profile
A15: APL Apollo Tubes Ltd is India’s largest producer of structural steel tubes and one of the world’s largest downstream steel companies outside China.
A16: It manufactures ERW steel tubes, GP and GI tubes, and pre-painted Alu-Zinc sheets, used widely in infrastructure, housing, solar, and industrial applications.
A18: Key Operations
A20: Main Activity: Manufacturing & selling of structural steel tubes and sheets (100% of turnover)
... A34: Scale & Market Position
A36: Metric | B36: FY 2025
A37: Manufacturing Capacity | B37: 4.5 million tons
A38: Market Share (India) | B38: 0.55
A39: Sales Volume | B39: 3.1 million tons
A40: Revenue | B40: ₹ 206,895 million
A41: Net Cash Position | B41: > ₹ 3 billion
A42: EBITDA per ton (FY25 blended)** | B42: ₹ ≈ 4,000–5,000
A45: Vision, Mission & Values
A47: Vision: To be a global leader and high-performing organization recognized for excellence, governance, customer delight, and long-term relationships.
A49: Mission: To lead the transformation from commodity to value-added products through innovation and technology.
A51: Core Values: Example | Commitment | Trust | Innovation | Integrity
A52: Governance & Leadership
A54: Chairman & Managing Director: Mr. Sanjay Gupta
A56: Group CFO & Director Operations: Mr. Deepak Goyal
A58: Company Secretary: Mr. Vipul Jain
A60: Statutory Auditors: Deloitte Haskins & Sells LLP
A64: Financial Highlights (Standalone FY 2025)
A66: Total Equity: ₹ 3,086.8 crore
A68: Net Debt: ₹ 34.4 crore (gearing ratio 0.01)
... A72: Subsidiaries: Apollo Metalex Ltd, APL Apollo Building Products Ltd, Blue Ocean Projects Pvt Ltd, APL Apollo Mart Ltd, APL Apollo Tubes LLC (UAE)
