Workbook

Sheet Income Statement
A1: Company Name:
A2: Comparative /Horizontal Analysis
A3: Income Statement
A5: Particulars | B5: 2022 | C5: 2021 | D5: 2020
A6: Revenue | B6: 5705 | C6: 2547 | D6: 3468
A7: % Change | B7: =(C6-B6)/C6 -> -1.2398901 | C7: =(D6-C6)/D6 -> 0.26557093
A8: COGS | B8: =B6*(40%+6%) -> 2624.3 | C8: =C6*(22%+3%) -> 636.75 | D8: =D6*(10%+4%) -> 485.52
A9: % Change | B9: =(C8-B8)/C8 -> -3.1213977 | C9: =(D8-C8)/D8 -> -0.31148047
A10: Gross Profit | B10: =B6-B9 -> 5708.1214 | C10: =C6-C8 -> 1910.25 | D10: =D6-D8 -> 2982.48
A11: % Change | B11: =(C10-B10)/C10 -> -1.9881541 | C11: =(D10-C10)/D10 -> 0.35950954
A12: Operating Expenses | B12: =B6-B8-Sheet1!D7 -> 6098.7 | C12: =C6-C8-Sheet1!C7 -> 2923.25 | D12: =D6-D8-'Income Statement'!B7 -> 2983.7199
A13: % Change | B13: =C10-B10/B10 -> 1909.25 | C13: =C10-C12/C10 -> 1908.7197
A14: Operating Profit | B14: =B10-B13 -> 3798.8714 | C14: =C10-C12 -> -1013 | D14: =D10-D12 -> -1.2398901
A15: % Change | B15: ='Income Statement'!B14/'Income Statement'!D5*100 -> 188.06294 | C15: =C14/'Income Statement'!C5*100 -> -50.123701 | D15: =D14/'Income Statement'!B5*100 -> -0.061319984
A16: Interest | B16: 43 | C16: 74 | D16: 82
A17: % Change | B17: =(C16-B16)/C16 -> 0.41891892 | C17: =D16-C16/D16 -> 81.097561
A18: Profit Before Tax | B18: -3768 | C18: -1314 | D18: -3768
A19: % Change | B19: =C18-B18/C18 -> -1316.8676 | C19: =D18-C18/D18 -> -3768.3487
A20: Tax | B20: 0 | C20: 0 | D20: 0
A21: % Change
A22: Profit after Tax | B22: =B18-B20 -> -3768 | C22: =C18-C20 -> -1314 | D22: =D18-D20 -> -3768
A23: % Change | B23: =C22-B22/C22 -> -1316.8676 | C23: =C22-B22/C22 -> -1316.8676
A25: Discussion Points
A26: Which items are changing majorly (increase or decrease)
A27: Seek Clarification for increase from annual reports if possible
A28: Which items do not show major change
A29: Are profits Changing as per Revenue
A30: Cost as a percentage of Sales | C30: 2022 | D30: 2021 | E30: 2020
A31: Margin Ratios
A32: Gross Profit Margin
A33: Operating Profit Margin
A34: Net Profit Margin
A35: Trend Analysis

Sheet Sheet1
A1: Profit & Loss
A2: Standalone Figures in Rs. Crores / View Consolidated
A3: Related Party
B4: 43891 | C4: 44256 | D4: 44621 | E4: 44986 | F4: 45352 | G4: 45717 | H4: TTM
A5: Sales + | B5: 3288 | C5: 2008 | D5: 3557 | E5: 4653 | F5: 6372 | G5: 8796 | H5: 9537
A6: Expenses + | B6: 6937 | C6: 3021 | D6: 6575 | E6: 8730 | F6: 8661 | G6: 11810 | H6: 13050
A7: Operating Profit | B7: -3650 | C7: -1013 | D7: -3018 | E7: -4077 | F7: -2289 | G7: -3013 | H7: -3513
A8: OPM % | B8: -1.11 | C8: -0.5 | D8: -0.85 | E8: -0.88 | F8: -0.36 | G8: -0.34 | H8: -0.37
A9: Other Income + | B9: 158 | C9: -24 | D9: -586 | E9: 475 | F9: 541 | G9: 590 | H9: 593
A10: Interest | B10: 82 | C10: 74 | D10: 43 | E10: 28 | F10: 22 | G10: 18 | H10: 17
A11: Depreciation | B11: 195 | C11: 203 | D11: 121 | E11: 128 | F11: 117 | G11: 100 | H11: 98
A12: Profit before tax | B12: -3768 | C12: -1314 | D12: -3768 | E12: -3758 | F12: -1888 | G12: -2542 | H12: -3035
A13: Tax % | B13: 0 | C13: 0 | D13: 0 | E13: 0 | F13: 0 | G13: 0
A14: Net Profit + | B14: -3768 | C14: -1314 | D14: -3768 | E14: -3758 | F14: -1888 | G14: -2542 | H14: -3035
A15: EPS in Rs | G15: -11.12 | H15: -60.03
A16: Dividend Payout % | B16: 0 | C16: 0 | D16: 0 | E16: 0 | F16: 0 | G16: 0
A17: Compounded Sales Growth
A18: 10 Years: | B18: %
A19: 5 Years: | B19: 0.22
A20: 3 Years: | B20: 0.35
A21: TTM: | B21: 0.37
A22: Compounded Profit Growth
A23: 10 Years: | B23: %
A24: 5 Years: | B24: 0.06
A25: 3 Years: | B25: 0.02
A26: TTM: | B26: -0.66
A27: Stock Price CAGR
A28: 10 Years: | B28: %
A29: 5 Years: | B29: %
A30: 3 Years: | B30: %
A31: 1 Year: | B31: %
A32: Return on Equity
A33: 10 Years: | B33: %
A34: 5 Years: | B34: %
A35: 3 Years: | B35: %
A36: Last Year: | B36: -0.92

Sheet IS -Vertical Analysis
A1: Company Name:
G2: Vertical Analysis
A3: Income Statement
G4: Revenue as Base
A5: Particulars | B5: 2022 | C5: 2021 | D5: 2020 | G5: Particulars | H5: 2022 | I5: 2021 | J5: 2020
A6: Revenue | B6: 1200 | C6: 1100 | D6: 979 | G6: Revenue | H6: =B6/B6 -> 1 | I6: =C6/C6 -> 1 | J6: =D6/D6 -> 1
A7: COGS | B7: 120 | C7: 110 | D7: 93 | G7: COGS | H7: =B7/B6 -> 0.1 | I7: =C7/C6 -> 0.1 | J7: =D7/D6 -> 0.094994893
A8: Gross Profit | B8: 5708 | C8: 1910 | D8: 2982 | G8: Gross Profit
A9: Operating Expenses | B9: 6098.7 | C9: 2932.7 | D9: 2983.72 | G9: Operating Expenses
A10: Operating Profit | G10: Operating Profit
A11: Interest | G11: Interest
A12: Profit Before Tax | G12: Profit Before Tax
A13: Tax | G13: Tax
A14: Profit after Tax | G14: Profit after Tax
A16: Discussion Points
A17: Which items are changing majorly wrt revenue
A18: Seek Clarification for increase in a particular year from annual reports if possible
A19: Which items do not show major change
A20: Are profits Changing as per Revenue
